pypiserver_backend_s3/__init__.py
pypiserver_backend_s3/backend.py
pypiserver_backend_s3-0.0.2.dist-info/LICENSE
pypiserver_backend_s3-0.0.2.dist-info/METADATA
pypiserver_backend_s3-0.0.2.dist-info/WHEEL
pypiserver_backend_s3-0.0.2.dist-info/entry_points.txt
pypiserver_backend_s3-0.0.2.dist-info/top_level.txt
pypiserver_backend_s3-0.0.2.dist-info/RECORD
