Metadata-Version: 2.1
Name: pypiserver-backend-s3
Version: 0.0.2
Summary: A pypiserver backend for storing packages directly to S3 (using boto3)
Author-email: Estelle Poulin <dev@inspiredby.es>
License: MIT
Project-URL: homepage, https://github.com/estheruary/pypiserver-backend-s3
Project-URL: repository, https://github.com/estheruary/pypiserver-backend-s3
Project-URL: changelog, https://github.com/estheruary/pypiserver-backend-s3/blob/main/README.md
Keywords: pypiserver
Classifier: Programming Language :: Python :: 3
Requires-Python: >=3.11
License-File: LICENSE
Requires-Dist: boto3 ==1.28.32
